torchedit/__init__.py
torchedit/main.py
torchedit-0.1.dist-info/METADATA
torchedit-0.1.dist-info/WHEEL
torchedit-0.1.dist-info/top_level.txt
torchedit-0.1.dist-info/RECORD
